airun_hwp/__init__.py
airun_hwp/cli.py
airun_hwp/cli_click.py
airun_hwp/cli_simple.py
airun_hwp/models/__init__.py
airun_hwp/models/content.py
airun_hwp/models/document.py
airun_hwp/models/document_v2.py
airun_hwp/models/metadata.py
airun_hwp/reader/__init__.py
airun_hwp/reader/hwp_reader.py
airun_hwp/reader/hwp_reader_improved.py
airun_hwp/reader/hwpx_reader.py
airun_hwp/reader/hwpx_reader_ordered.py
airun_hwp/reader/hwpx_reader_ordered_v2.py
airun_hwp/writer/__init__.py
airun_hwp/writer/hwpx_writer.py
airun_hwp/writer/pdf_converter.py
airun_hwp/writer/pdf_converter_libreoffice.py
airun_hwp/writer/pdf_to_image.py
airun_hwp-0.3.1.dist-info/licenses/LICENSE
airun_hwp-0.3.1.dist-info/METADATA
airun_hwp-0.3.1.dist-info/WHEEL
airun_hwp-0.3.1.dist-info/entry_points.txt
airun_hwp-0.3.1.dist-info/top_level.txt
airun_hwp-0.3.1.dist-info/RECORD
