Metadata-Version: 2.4
Name: airun-hwp
Version: 0.3.1
Summary: AI-powered HWP/HWPX document processing library for Hamonize
Author-email: Kevin Kim <chaeya@gmail.com>
License: MIT License
Project-URL: Homepage, https://github.com/chaeya/airun-hwp
Project-URL: Repository, https://github.com/chaeya/airun-hwp.git
Project-URL: Issues, https://github.com/chaeya/airun-hwp/issues
Keywords: hwp,hwpx,document,parser,hancom,hamonize
Classifier: Development Status :: 3 - Alpha
Classifier: Intended Audience :: Developers
Classifier: Programming Language :: Python :: 3
Classifier: Programming Language :: Python :: 3.8
Classifier: Programming Language :: Python :: 3.9
Classifier: Programming Language :: Python :: 3.10
Classifier: Programming Language :: Python :: 3.11
Classifier: Programming Language :: Python :: 3.12
Requires-Python: >=3.8
License-File: LICENSE
Requires-Dist: pypandoc-hwpx>=0.1.0
Requires-Dist: PyYAML>=6.0
Requires-Dist: Pillow>=10.0.0
Requires-Dist: weasyprint>=60.0
Requires-Dist: markdown>=3.5.0
Requires-Dist: click>=8.0.0
Provides-Extra: dev
Requires-Dist: pytest>=7.0; extra == "dev"
Requires-Dist: pytest-cov>=4.0; extra == "dev"
Requires-Dist: pytest-mock>=3.10; extra == "dev"
Requires-Dist: pytest-xdist>=3.0; extra == "dev"
Requires-Dist: black>=23.0; extra == "dev"
Requires-Dist: ruff>=0.1.0; extra == "dev"
Requires-Dist: mypy>=1.0; extra == "dev"
Requires-Dist: types-PyYAML>=6.0; extra == "dev"
Dynamic: license-file
